smtpymailer/__init__.py
smtpymailer/html_parse.py
smtpymailer/mailer.py
smtpymailer/types.py
smtpymailer/utils.py
smtpymailer/validation.py
smtpymailer-0.1.10.dist-info/METADATA
smtpymailer-0.1.10.dist-info/WHEEL
smtpymailer-0.1.10.dist-info/top_level.txt
smtpymailer-0.1.10.dist-info/RECORD
