Metadata-Version: 2.2
Name: smtpymailer
Version: 0.1.10
Summary: A emailing python library for emailing from alternative domains - DNS entries etc need to be assigned (not used for spamming).
Home-page: https://github.com/lewis-morris/smtpymailer
Author: Lewis Morris
Author-email: lewis@arched.dev
License: MIT
Classifier: Programming Language :: Python :: 3
Classifier: License :: OSI Approved :: MIT License
Classifier: Operating System :: OS Independent
Requires-Python: >=3.7
Requires-Dist: validators>=0.22.0
Requires-Dist: dnspython>=2.6.1
Requires-Dist: pydig>=0.4.0
Requires-Dist: python-dotenv>=1.0.1
Requires-Dist: requests>=2.32.3
Requires-Dist: html2text>=2024.2.26
Requires-Dist: beautifulsoup4>=4.13.3
Requires-Dist: Jinja2>=3.1.5
Requires-Dist: pillow>=10.2.0
Requires-Dist: email_validator>=2.2.0
Provides-Extra: dev
Requires-Dist: pytest; extra == "dev"
Requires-Dist: email-validator; extra == "dev"
Requires-Dist: mailinator-python-client-2==0.0.4; extra == "dev"
Requires-Dist: coverage; extra == "dev"
Requires-Dist: coverage-badge; extra == "dev"
Dynamic: author
Dynamic: author-email
Dynamic: classifier
Dynamic: description
Dynamic: description-content-type
Dynamic: home-page
Dynamic: license
Dynamic: provides-extra
Dynamic: requires-dist
Dynamic: requires-python
Dynamic: summary
